ym2021_prj/__init__.py
ym2021_prj/_version.py
ym2021_prj/cli.py
ym2021_prj/tests/__init__.py
ym2021_prj/tests/test_cli.py
ym2021_prj-0.2.1.dist-info/LICENSE
ym2021_prj-0.2.1.dist-info/METADATA
ym2021_prj-0.2.1.dist-info/WHEEL
ym2021_prj-0.2.1.dist-info/entry_points.txt
ym2021_prj-0.2.1.dist-info/top_level.txt
ym2021_prj-0.2.1.dist-info/RECORD
