Metadata-Version: 2.1
Name: ym2021-prj
Version: 0.2.1
Summary: Repository to test GitHub Actions Workflows.
Home-page: https://github.com/prjemian/ym2021_prj
Author: Pete R. Jemian
Author-email: prjemian@gmail.com
License: CC0 1.0 Universal
Keywords: Python test repository
Classifier: Development Status :: 3 - Alpha
Classifier: Topic :: Utilities
Classifier: License :: CC0 1.0 Universal (CC0 1.0) Public Domain Dedication
Classifier: Programming Language :: Python
Classifier: Programming Language :: Python :: 3
Classifier: Programming Language :: Python :: 3.7
Classifier: Programming Language :: Python :: 3.8
Classifier: Programming Language :: Python :: 3.9
Classifier: Programming Language :: Python :: 3.10
Classifier: Programming Language :: Python :: 3.11
Classifier: Topic :: Software Development
Requires-Python: >=3.8
License-File: LICENSE
Requires-Dist: numpy
Requires-Dist: pip
Requires-Dist: setuptools-scm
Provides-Extra: dev
Requires-Dist: coveralls ; extra == 'dev'
Requires-Dist: pytest ; extra == 'dev'
Requires-Dist: pytest-cov ; extra == 'dev'
Requires-Dist: setuptools-scm ; extra == 'dev'
